geoscan/__init__.py
geoscan/geoscan.py
geoscan-0.2.8.dist-info/METADATA
geoscan-0.2.8.dist-info/WHEEL
geoscan-0.2.8.dist-info/top_level.txt
geoscan-0.2.8.dist-info/RECORD
