Metadata-Version: 2.1
Name: geoscan
Version: 0.2.8
Summary: Geoclustering using H3 hexagons
Home-page: https://github.com/aamend/geoscan
Author: Antoine Amend
Author-email: antoine.amend@databricks.com
License: UNKNOWN
Platform: UNKNOWN
Classifier: Programming Language :: Python :: 3
Classifier: Operating System :: OS Independent
Provides-Extra: tests
Requires-Dist: pytest ; extra == 'tests'
